{
    "subject_name": "Digital Forensics",
    "known_as": "DF",
    "subjecet_code": "3170725",
    "syllabus": "https://bit.ly/3Hcgy1U",
    "old_paper": [
        {
            "year": "Summer-22",
            "link": "https://gtu.ac.in/uploads/S2022/BE/3170725.pdf"
        },
        {
            "year": "Winter-21",
            "link": "https://gtu.ac.in/uploads/W2021/BE/3170725.pdf"
        }
    ],
    "paper_solution": [],
    "prectical": "",
    "viva_questions": "",
    "imp_material": "",
    "assignments": "",
    "Books": []
}